degirum_cli/__init__.py
degirum_cli/_version.py
degirum_cli/benchmark.py
degirum_cli/cli.py
degirum_cli/predict_image.py
degirum_cli/predict_video.py
degirum_cli-0.1.0.dist-info/LICENSE
degirum_cli-0.1.0.dist-info/METADATA
degirum_cli-0.1.0.dist-info/WHEEL
degirum_cli-0.1.0.dist-info/entry_points.txt
degirum_cli-0.1.0.dist-info/top_level.txt
degirum_cli-0.1.0.dist-info/RECORD
