Metadata-Version: 2.1
Name: degirum_cli
Version: 0.1.0
Summary: Degirum AI package with CLI for image and video prediction
Author: DeGirum
Classifier: Programming Language :: Python :: 3
Classifier: License :: OSI Approved :: MIT License
Requires-Python: >=3.8
License-File: LICENSE
Requires-Dist: click
Requires-Dist: pyyaml
Requires-Dist: degirum
Requires-Dist: degirum-tools
